{"voltilamm":{"game":"PT","exists":true,"name":"voltilamm","eggGroup1":"Monster","eggGroup2":"Feld","gender":"both","lowestEvo":"voltilamm","evolutions":["waaty","ampharos"],"unpairable":false,"unbreedable":false,"directLearnsets":["Magnetflug","Schnarcher","Sternschauer"],"breedingLearnsets":[],"eventLearnsets":[],"oldGenLearnsets":["Kopfnuss"]},"voltobal":{"game":"PT","exists":true,"name":"voltobal","eggGroup1":"Mineral","eggGroup2":"","gender":"unknown","lowestEvo":"voltobal","evolutions":["lektrobal"],"unpairable":false,"unbreedable":false,"directLearnsets":["Ampelleuchte","Schnarcher","Tiefschlag"],"breedingLearnsets":[],"eventLearnsets":[],"oldGenLearnsets":["Kopfnuss"]},"hisui-voltobal":{"game":"PT","exists":false,"name":"hisui-voltobal","eggGroup1":"Mineral","eggGroup2":"","gender":"unknown","lowestEvo":"hisui-voltobal","evolutions":["hisui-lektrobal"],"unpairable":false,"unbreedable":false,"directLearnsets":[],"breedingLearnsets":[],"eventLearnsets":[],"oldGenLearnsets":[]},"voltolos":{"game":"PT","exists":false,"name":"voltolos","eggGroup1":"Unbekannt","eggGroup2":"","gender":"male","lowestEvo":"voltolos","evolutions":[],"unpairable":true,"unbreedable":true,"directLearnsets":[],"breedingLearnsets":[],"eventLearnsets":[],"oldGenLearnsets":[]},"voltolos (inkarnationsform)":{"game":"PT","exists":false,"name":"voltolos (inkarnationsform)","eggGroup1":"Unbekannt","eggGroup2":"","gender":"male","lowestEvo":"","unpairable":true,"unbreedable":true,"directLearnsets":[],"breedingLearnsets":[],"eventLearnsets":[],"oldGenLearnsets":[]},"voltriant":{"game":"PT","exists":false,"name":"voltriant","eggGroup1":"Unbekannt","eggGroup2":"","gender":"unknown","lowestEvo":"voltriant","evolutions":[],"unpairable":true,"unbreedable":true,"directLearnsets":[],"breedingLearnsets":[],"eventLearnsets":[],"oldGenLearnsets":[]},"voltula":{"game":"PT","exists":false,"name":"voltula","eggGroup1":"Käfer","eggGroup2":"","gender":"both","lowestEvo":"wattzapf","evolutions":[],"unpairable":false,"unbreedable":true,"directLearnsets":[],"breedingLearnsets":[],"eventLearnsets":[],"oldGenLearnsets":[]},"voluminas":{"game":"PT","exists":true,"name":"voluminas","eggGroup1":"Mineral","eggGroup2":"","gender":"both","lowestEvo":"nasgnet","evolutions":[],"unpairable":false,"unbreedable":true,"directLearnsets":["Juwelenkraft","Antik-Kraft","Donnerschlag","Eisenschädel","Eishieb","Feuerschlag","Lehmschelle","Schnarcher","Walzer"],"breedingLearnsets":[],"eventLearnsets":[],"oldGenLearnsets":[]},"vulnona":{"game":"PT","exists":true,"name":"vulnona","eggGroup1":"Feld","eggGroup2":"","gender":"both","lowestEvo":"vulpix","evolutions":[],"unpairable":false,"unbreedable":true,"directLearnsets":["Groll","Hitzewelle","Schnarcher","Sternschauer","Unheilböen","Zen-Kopfstoß"],"breedingLearnsets":[],"eventLearnsets":[],"oldGenLearnsets":["Kopfnuss"]},"alola-vulnona":{"game":"PT","exists":false,"name":"alola-vulnona","eggGroup1":"Feld","eggGroup2":"","gender":"both","lowestEvo":"alola-vulpix","evolutions":[],"unpairable":false,"unbreedable":true,"directLearnsets":[],"breedingLearnsets":[],"eventLearnsets":[],"oldGenLearnsets":[]},"vulpix":{"game":"PT","exists":true,"name":"vulpix","eggGroup1":"Feld","eggGroup2":"","gender":"both","lowestEvo":"vulpix","evolutions":["vulnona"],"unpairable":false,"unbreedable":false,"directLearnsets":["Groll","Hitzewelle","Schnarcher","Sternschauer","Unheilböen","Zen-Kopfstoß"],"breedingLearnsets":[],"eventLearnsets":[],"oldGenLearnsets":["Kopfnuss"]},"alola-vulpix":{"game":"PT","exists":false,"name":"alola-vulpix","eggGroup1":"Feld","eggGroup2":"","gender":"both","lowestEvo":"alola-vulpix","evolutions":["alola-vulnona"],"unpairable":false,"unbreedable":false,"directLearnsets":[],"breedingLearnsets":[],"eventLearnsets":[],"oldGenLearnsets":[]},"waaty":{"game":"PT","exists":true,"name":"waaty","eggGroup1":"Monster","eggGroup2":"Feld","gender":"both","lowestEvo":"voltilamm","evolutions":["ampharos"],"unpairable":false,"unbreedable":true,"directLearnsets":["Donnerschlag","Feuerschlag","Magnetflug","Schnarcher","Sternschauer"],"breedingLearnsets":[],"eventLearnsets":[],"oldGenLearnsets":["Kopfnuss"]},"wablu":{"game":"PT","exists":true,"name":"wablu","eggGroup1":"Flug","eggGroup2":"Drache","gender":"both","lowestEvo":"wablu","evolutions":["altaria"],"unpairable":false,"unbreedable":false,"directLearnsets":["Aufruhr","Hitzewelle","Lehmschelle","Schnarcher","Sternschauer","Unheilböen","Windhose","Windschnitt","Wutanfall"],"breedingLearnsets":[],"eventLearnsets":[],"oldGenLearnsets":[]},"wadribie":{"game":"PT","exists":true,"name":"wadribie","eggGroup1":"Käfer","eggGroup2":"","gender":"both","lowestEvo":"wadribie","evolutions":["honweisel"],"unpairable":false,"unbreedable":false,"directLearnsets":["Käferbiss","Lehmschelle","Notsituation","Schnarcher","Sternschauer","Unheilböen","Windschnitt"],"breedingLearnsets":[],"eventLearnsets":[],"oldGenLearnsets":[]},"wagong":{"game":"PT","exists":false,"name":"wagong","eggGroup1":"Mineral","eggGroup2":"","gender":"both","lowestEvo":"klonkett","evolutions":["montecarbo"],"unpairable":false,"unbreedable":true,"directLearnsets":[],"breedingLearnsets":[],"eventLearnsets":[],"oldGenLearnsets":[]},"wailmer":{"game":"PT","exists":true,"name":"wailmer","eggGroup1":"Feld","eggGroup2":"Wasser 2","gender":"both","lowestEvo":"wailmer","evolutions":["wailord"],"unpairable":false,"unbreedable":false,"directLearnsets":["Eissturm","Schnarcher"],"breedingLearnsets":[],"eventLearnsets":[],"oldGenLearnsets":[]},"wailord":{"game":"PT","exists":true,"name":"wailord","eggGroup1":"Feld","eggGroup2":"Wasser 2","gender":"both","lowestEvo":"wailmer","evolutions":[],"unpairable":false,"unbreedable":true,"directLearnsets":["Eisenschädel","Eissturm","Schnarcher"],"breedingLearnsets":[],"eventLearnsets":[],"oldGenLearnsets":[]},"walraisa":{"game":"PT","exists":true,"name":"walraisa","eggGroup1":"Wasser 1","eggGroup2":"Feld","gender":"both","lowestEvo":"seemops","evolutions":[],"unpairable":false,"unbreedable":true,"directLearnsets":["Ampelleuchte","Eisenschädel","Eissturm","Lehmschelle","Nassschweif","Taucher","Walzer","Zornklinge"],"breedingLearnsets":[],"eventLearnsets":[],"oldGenLearnsets":[]},"washakwil":{"game":"PT","exists":false,"name":"washakwil","eggGroup1":"Flug","eggGroup2":"","gender":"male","lowestEvo":"geronimatz","evolutions":[],"unpairable":false,"unbreedable":true,"directLearnsets":[],"breedingLearnsets":[],"eventLearnsets":[],"oldGenLearnsets":[]},"hisui-washakwil":{"game":"PT","exists":false,"name":"hisui-washakwil","eggGroup1":"Flug","eggGroup2":"","gender":"male","lowestEvo":"geronimatz","evolutions":[],"unpairable":false,"unbreedable":true,"directLearnsets":[],"breedingLearnsets":[],"eventLearnsets":[],"oldGenLearnsets":[]},"wattzapf":{"game":"PT","exists":false,"name":"wattzapf","eggGroup1":"Käfer","eggGroup2":"","gender":"both","lowestEvo":"wattzapf","evolutions":["voltula"],"unpairable":false,"unbreedable":false,"directLearnsets":[],"breedingLearnsets":[],"eventLearnsets":[],"oldGenLearnsets":[]},"waumboll":{"game":"PT","exists":false,"name":"waumboll","eggGroup1":"Pflanze","eggGroup2":"Fee","gender":"both","lowestEvo":"waumboll","evolutions":["elfun"],"unpairable":false,"unbreedable":false,"directLearnsets":[],"breedingLearnsets":[],"eventLearnsets":[],"oldGenLearnsets":[]},"waumpel":{"game":"PT","exists":true,"name":"waumpel","eggGroup1":"Käfer","eggGroup2":"","gender":"both","lowestEvo":"waumpel","evolutions":["schaloko","papinella","panekon","pudox"],"unpairable":false,"unbreedable":false,"directLearnsets":["Käferbiss","Schnarcher"],"breedingLearnsets":[],"eventLearnsets":[],"oldGenLearnsets":[]},"webarak":{"game":"PT","exists":true,"name":"webarak","eggGroup1":"Käfer","eggGroup2":"","gender":"both","lowestEvo":"webarak","evolutions":["ariados"],"unpairable":false,"unbreedable":false,"directLearnsets":["Ampelleuchte","Sprungfeder"],"breedingLearnsets":[],"eventLearnsets":[],"oldGenLearnsets":[]},"welsar":{"game":"PT","exists":true,"name":"welsar","eggGroup1":"Wasser 2","eggGroup2":"","gender":"both","lowestEvo":"schmerbe","evolutions":[],"unpairable":false,"unbreedable":true,"directLearnsets":["Eissturm","Erdkräfte","Sprungfeder","Taucher"],"breedingLearnsets":[],"eventLearnsets":[],"oldGenLearnsets":[]},"wie-shu":{"game":"PT","exists":false,"name":"wie-shu","eggGroup1":"Feld","eggGroup2":"Humanotyp","gender":"both","lowestEvo":"lin-fu","evolutions":[],"unpairable":false,"unbreedable":true,"directLearnsets":[],"breedingLearnsets":[],"eventLearnsets":[],"oldGenLearnsets":[]},"wielie":{"game":"PT","exists":true,"name":"wielie","eggGroup1":"Wasser 3","eggGroup2":"","gender":"both","lowestEvo":"liliep","evolutions":[],"unpairable":false,"unbreedable":true,"directLearnsets":["Erdkräfte","Lehmschelle","Samenbomben","Schnarcher","Synthese"],"breedingLearnsets":[],"eventLearnsets":[],"oldGenLearnsets":[]},"wiesenior":{"game":"PT","exists":true,"name":"wiesenior","eggGroup1":"Feld","eggGroup2":"","gender":"both","lowestEvo":"wiesor","evolutions":[],"unpairable":false,"unbreedable":true,"directLearnsets":["Abschlag","Aufruhr","Donnerschlag","Eishieb","Feuerschlag","Lehmschelle","Nassschweif","Schnarcher","Sternschauer","Walzer","Zornklinge","Zuflucht"],"breedingLearnsets":[],"eventLearnsets":[],"oldGenLearnsets":["Kopfnuss"]},"wiesor":{"game":"PT","exists":true,"name":"wiesor","eggGroup1":"Feld","eggGroup2":"","gender":"both","lowestEvo":"wiesor","evolutions":["wiesenior"],"unpairable":false,"unbreedable":false,"directLearnsets":["Abschlag","Aufruhr","Donnerschlag","Eishieb","Feuerschlag","Lehmschelle","Nassschweif","Schnarcher","Sternschauer","Walzer","Zornklinge","Zuflucht"],"breedingLearnsets":[],"eventLearnsets":[],"oldGenLearnsets":["Kopfnuss"]},"wingull":{"game":"PT","exists":true,"name":"wingull","eggGroup1":"Wasser 1","eggGroup2":"Flug","gender":"both","lowestEvo":"wingull","evolutions":["pelipper"],"unpairable":false,"unbreedable":false,"directLearnsets":["Auflockern","Abschlag","Aufruhr","Eissturm","Lehmschelle","Schnarcher","Sternschauer","Unheilböen","Windhose","Windschnitt"],"breedingLearnsets":[],"eventLearnsets":[],"oldGenLearnsets":[]},"woingenau":{"game":"PT","exists":true,"name":"woingenau","eggGroup1":"Amorph","eggGroup2":"","gender":"both","lowestEvo":"isso","evolutions":[],"unpairable":false,"unbreedable":false,"directLearnsets":[],"breedingLearnsets":[],"eventLearnsets":[],"oldGenLearnsets":[]},"wolly":{"game":"PT","exists":false,"name":"wolly","eggGroup1":"Feld","eggGroup2":"","gender":"both","lowestEvo":"wolly","evolutions":["zwollock"],"unpairable":false,"unbreedable":false,"directLearnsets":[],"breedingLearnsets":[],"eventLearnsets":[],"oldGenLearnsets":[]},"wolwerock":{"game":"PT","exists":false,"name":"wolwerock","eggGroup1":"Feld","eggGroup2":"","gender":"both","lowestEvo":"wuffels","evolutions":[],"unpairable":false,"unbreedable":true,"directLearnsets":[],"breedingLearnsets":[],"eventLearnsets":[],"oldGenLearnsets":[]},"wolwerock (nachtform)":{"game":"PT","exists":false,"name":"wolwerock (nachtform)","eggGroup1":"Feld","eggGroup2":"","gender":"both","lowestEvo":"wuffels","evolutions":[],"unpairable":false,"unbreedable":true,"directLearnsets":[],"breedingLearnsets":[],"eventLearnsets":[],"oldGenLearnsets":[]},"wolwerock (zwielichtform)":{"game":"PT","exists":false,"name":"wolwerock (zwielichtform)","eggGroup1":"Feld","eggGroup2":"","gender":"both","lowestEvo":"wuffels","evolutions":[],"unpairable":false,"unbreedable":true,"directLearnsets":[],"breedingLearnsets":[],"eventLearnsets":[],"oldGenLearnsets":[]},"wommel":{"game":"PT","exists":false,"name":"wommel","eggGroup1":"Käfer","eggGroup2":"Fee","gender":"both","lowestEvo":"wommel","evolutions":["bandelby"],"unpairable":false,"unbreedable":false,"directLearnsets":[],"breedingLearnsets":[],"eventLearnsets":[],"oldGenLearnsets":[]},"wonneira":{"game":"PT","exists":true,"name":"wonneira","eggGroup1":"Fee","eggGroup2":"","gender":"female","lowestEvo":"wonneira","evolutions":["chaneira","heiteira"],"unpairable":true,"unbreedable":false,"directLearnsets":["Aufruhr","Eissturm","Lehmschelle","Notsituation","Rechte Hand","Schnarcher","Walzer","Zen-Kopfstoß","Zuflucht"],"breedingLearnsets":[],"eventLearnsets":[],"oldGenLearnsets":[]},"wuffels":{"game":"PT","exists":false,"name":"wuffels","eggGroup1":"Feld","eggGroup2":"","gender":"both","lowestEvo":"wuffels","evolutions":["wolwerock (tagform)","wolwerock (nachtform)","wolwerock (zwielichtform)","wolwerock"],"unpairable":false,"unbreedable":false,"directLearnsets":[],"breedingLearnsets":[],"eventLearnsets":[],"oldGenLearnsets":[]},"wulaosu":{"game":"PT","exists":false,"name":"wulaosu","eggGroup1":"Unbekannt","eggGroup2":"","gender":"both","lowestEvo":"wulaosu","evolutions":[],"unpairable":true,"unbreedable":true,"directLearnsets":[],"breedingLearnsets":[],"eventLearnsets":[],"oldGenLearnsets":[]},"wulaosu (fließender stil)":{"game":"PT","exists":false,"name":"wulaosu (fließender stil)","eggGroup1":"Unbekannt","eggGroup2":"","gender":"both","lowestEvo":"dakuma","evolutions":[],"unpairable":true,"unbreedable":true,"directLearnsets":[],"breedingLearnsets":[],"eventLearnsets":[],"oldGenLearnsets":[]},"wummer":{"game":"PT","exists":false,"name":"wummer","eggGroup1":"Wasser 1","eggGroup2":"Wasser 3","gender":"both","lowestEvo":"scampisto","evolutions":[],"unpairable":false,"unbreedable":true,"directLearnsets":[],"breedingLearnsets":[],"eventLearnsets":[],"oldGenLearnsets":[]},"xatu":{"game":"PT","exists":true,"name":"xatu","eggGroup1":"Flug","eggGroup2":"","gender":"both","lowestEvo":"natu","evolutions":[],"unpairable":false,"unbreedable":true,"directLearnsets":["Auflockern","Ampelleuchte","Hitzewelle","Schnarcher","Sternschauer","Tiefschlag","Trickbetrug","Windhose","Windschnitt","Zen-Kopfstoß"],"breedingLearnsets":[],"eventLearnsets":[],"oldGenLearnsets":[]},"xerneas":{"game":"PT","exists":false,"name":"xerneas","eggGroup1":"Unbekannt","eggGroup2":"","gender":"unknown","lowestEvo":"xerneas","evolutions":[],"unpairable":true,"unbreedable":true,"directLearnsets":[],"breedingLearnsets":[],"eventLearnsets":[],"oldGenLearnsets":[]},"yanma":{"game":"PT","exists":true,"name":"yanma","eggGroup1":"Käfer","eggGroup2":"","gender":"both","lowestEvo":"yanma","evolutions":["yanmega"],"unpairable":false,"unbreedable":false,"directLearnsets":["Auflockern","Ampelleuchte","Schnarcher","Sternschauer","Unheilböen","Windschnitt"],"breedingLearnsets":[],"eventLearnsets":[],"oldGenLearnsets":["Kopfnuss"]},"yanmega":{"game":"PT","exists":true,"name":"yanmega","eggGroup1":"Käfer","eggGroup2":"","gender":"both","lowestEvo":"yanma","evolutions":[],"unpairable":false,"unbreedable":true,"directLearnsets":["Offenlegung","Auflockern","Ampelleuchte","Lehmschelle","Schnarcher","Sternschauer","Unheilböen","Windschnitt"],"breedingLearnsets":[],"eventLearnsets":[],"oldGenLearnsets":[]},"yorkleff":{"game":"PT","exists":false,"name":"yorkleff","eggGroup1":"Feld","eggGroup2":"","gender":"both","lowestEvo":"yorkleff","evolutions":["terribark","bissbark"],"unpairable":false,"unbreedable":false,"directLearnsets":[],"breedingLearnsets":[],"eventLearnsets":[],"oldGenLearnsets":[]},"yveltal":{"game":"PT","exists":false,"name":"yveltal","eggGroup1":"Unbekannt","eggGroup2":"","gender":"unknown","lowestEvo":"yveltal","evolutions":[],"unpairable":true,"unbreedable":true,"directLearnsets":[],"breedingLearnsets":[],"eventLearnsets":[],"oldGenLearnsets":[]},"zacian":{"game":"PT","exists":false,"name":"zacian","eggGroup1":"Unbekannt","eggGroup2":"","gender":"unknown","lowestEvo":"zacian","evolutions":[],"unpairable":true,"unbreedable":true,"directLearnsets":[],"breedingLearnsets":[],"eventLearnsets":[],"oldGenLearnsets":[]},"zamazenta":{"game":"PT","exists":false,"name":"zamazenta","eggGroup1":"Unbekannt","eggGroup2":"","gender":"unknown","lowestEvo":"zamazenta","evolutions":[],"unpairable":true,"unbreedable":true,"directLearnsets":[],"breedingLearnsets":[],"eventLearnsets":[],"oldGenLearnsets":[]},"zapdos":{"game":"PT","exists":true,"name":"zapdos","eggGroup1":"Unbekannt","eggGroup2":"","gender":"unknown","lowestEvo":"zapdos","evolutions":[],"unpairable":true,"unbreedable":true,"directLearnsets":["Auflockern","Ampelleuchte","Hitzewelle","Lehmschelle","Schnarcher","Sternschauer","Unheilböen","Windhose","Windschnitt"],"breedingLearnsets":[],"eventLearnsets":[],"oldGenLearnsets":[]},"galar-zapdos":{"game":"PT","exists":false,"name":"galar-zapdos","eggGroup1":"Unbekannt","eggGroup2":"","gender":"unknown","lowestEvo":"galar-zapdos","evolutions":[],"unpairable":true,"unbreedable":true,"directLearnsets":[],"breedingLearnsets":[],"eventLearnsets":[],"oldGenLearnsets":[]},"zapplalek":{"game":"PT","exists":false,"name":"zapplalek","eggGroup1":"Amorph","eggGroup2":"","gender":"both","lowestEvo":"zapplardin","evolutions":["zapplarang"],"unpairable":false,"unbreedable":true,"directLearnsets":[],"breedingLearnsets":[],"eventLearnsets":[],"oldGenLearnsets":[]},"zapplarang":{"game":"PT","exists":false,"name":"zapplarang","eggGroup1":"Amorph","eggGroup2":"","gender":"both","lowestEvo":"zapplardin","evolutions":[],"unpairable":false,"unbreedable":true,"directLearnsets":[],"breedingLearnsets":[],"eventLearnsets":[],"oldGenLearnsets":[]},"zapplardin":{"game":"PT","exists":false,"name":"zapplardin","eggGroup1":"Amorph","eggGroup2":"","gender":"both","lowestEvo":"zapplardin","evolutions":["zapplalek","zapplarang"],"unpairable":false,"unbreedable":false,"directLearnsets":[],"breedingLearnsets":[],"eventLearnsets":[],"oldGenLearnsets":[]},"zarude":{"game":"PT","exists":false,"name":"zarude","eggGroup1":"Unbekannt","eggGroup2":"","gender":"unknown","lowestEvo":"zarude","evolutions":[],"unpairable":true,"unbreedable":true,"directLearnsets":[],"breedingLearnsets":[],"eventLearnsets":[],"oldGenLearnsets":[]},"zebritz":{"game":"PT","exists":false,"name":"zebritz","eggGroup1":"Feld","eggGroup2":"","gender":"both","lowestEvo":"elezeba","evolutions":[],"unpairable":false,"unbreedable":true,"directLearnsets":[],"breedingLearnsets":[],"eventLearnsets":[],"oldGenLearnsets":[]},"zekrom":{"game":"PT","exists":false,"name":"zekrom","eggGroup1":"Unbekannt","eggGroup2":"","gender":"unknown","lowestEvo":"zekrom","evolutions":[],"unpairable":true,"unbreedable":true,"directLearnsets":[],"breedingLearnsets":[],"eventLearnsets":[],"oldGenLearnsets":[]},"zeraora":{"game":"PT","exists":false,"name":"zeraora","eggGroup1":"Unbekannt","eggGroup2":"","gender":"unknown","lowestEvo":"zeraora","evolutions":[],"unpairable":true,"unbreedable":true,"directLearnsets":[],"breedingLearnsets":[],"eventLearnsets":[],"oldGenLearnsets":[]},"zigzachs":{"game":"PT","exists":true,"name":"zigzachs","eggGroup1":"Feld","eggGroup2":"","gender":"both","lowestEvo":"zigzachs","evolutions":["geradaks"],"unpairable":false,"unbreedable":false,"directLearnsets":["Eissturm","Lehmschelle","Mülltreffer","Rechte Hand","Samenbomben","Schnarcher","Sternschauer","Trickbetrug","Walzer","Zornklinge","Zuflucht"],"breedingLearnsets":[],"eventLearnsets":[],"oldGenLearnsets":[]},"galar-zigzachs":{"game":"PT","exists":false,"name":"galar-zigzachs","eggGroup1":"Feld","eggGroup2":"","gender":"both","lowestEvo":"galar-zigzachs","evolutions":["galar-geradaks","barrikadax"],"unpairable":false,"unbreedable":false,"directLearnsets":[],"breedingLearnsets":[],"eventLearnsets":[],"oldGenLearnsets":[]},"zirpeise":{"game":"PT","exists":true,"name":"zirpeise","eggGroup1":"Käfer","eggGroup2":"","gender":"both","lowestEvo":"zirpurze","evolutions":[],"unpairable":false,"unbreedable":true,"directLearnsets":["Schlitzer","Verhöhner","Nachthieb","Abschlag","Aufruhr","Lehmschelle","Notsituation","Schnarcher"],"breedingLearnsets":[],"eventLearnsets":[],"oldGenLearnsets":[]},"zirpurze":{"game":"PT","exists":true,"name":"zirpurze","eggGroup1":"Käfer","eggGroup2":"","gender":"both","lowestEvo":"zirpurze","evolutions":["zirpeise"],"unpairable":false,"unbreedable":false,"directLearnsets":["Käferbiss","Aufruhr","Lehmschelle","Notsituation","Schnarcher"],"breedingLearnsets":[],"eventLearnsets":[],"oldGenLearnsets":[]},"zobiris":{"game":"PT","exists":true,"name":"zobiris","eggGroup1":"Humanotyp","eggGroup2":"","gender":"both","lowestEvo":"zobiris","evolutions":[],"unpairable":false,"unbreedable":false,"directLearnsets":["Ampelleuchte","Donnerschlag","Eishieb","Eissturm","Feuerschlag","Groll","Lehmschelle","Schnarcher","Tiefschlag","Trickbetrug","Unheilböen","Zornklinge"],"breedingLearnsets":[],"eventLearnsets":[],"oldGenLearnsets":[]},"zoroark":{"game":"PT","exists":false,"name":"zoroark","eggGroup1":"Feld","eggGroup2":"","gender":"both","lowestEvo":"zorua","evolutions":[],"unpairable":false,"unbreedable":true,"directLearnsets":[],"breedingLearnsets":[],"eventLearnsets":[],"oldGenLearnsets":[]},"hisui-zoroark":{"game":"PT","exists":false,"name":"hisui-zoroark","eggGroup1":"Feld","eggGroup2":"","gender":"both","lowestEvo":"hisui-zorua","evolutions":[],"unpairable":false,"unbreedable":true,"directLearnsets":[],"breedingLearnsets":[],"eventLearnsets":[],"oldGenLearnsets":[]},"zorua":{"game":"PT","exists":false,"name":"zorua","eggGroup1":"Feld","eggGroup2":"","gender":"both","lowestEvo":"zorua","evolutions":["zoroark"],"unpairable":false,"unbreedable":false,"directLearnsets":[],"breedingLearnsets":[],"eventLearnsets":[],"oldGenLearnsets":[]},"hisui-zorua":{"game":"PT","exists":false,"name":"hisui-zorua","eggGroup1":"Feld","eggGroup2":"","gender":"both","lowestEvo":"hisui-zorua","evolutions":["hisui-zoroark"],"unpairable":false,"unbreedable":false,"directLearnsets":[],"breedingLearnsets":[],"eventLearnsets":[],"oldGenLearnsets":[]},"zubat":{"game":"PT","exists":true,"name":"zubat","eggGroup1":"Flug","eggGroup2":"","gender":"both","lowestEvo":"zubat","evolutions":["golbat","iksbat"],"unpairable":false,"unbreedable":false,"directLearnsets":["Auflockern","Aufruhr","Hitzewelle","Schnarcher","Sternschauer","Unheilböen","Windhose","Zen-Kopfstoß"],"breedingLearnsets":[],"eventLearnsets":[],"oldGenLearnsets":[]},"zurrokex":{"game":"PT","exists":false,"name":"zurrokex","eggGroup1":"Feld","eggGroup2":"Drache","gender":"both","lowestEvo":"zurrokex","evolutions":["irokex"],"unpairable":false,"unbreedable":false,"directLearnsets":[],"breedingLearnsets":[],"eventLearnsets":[],"oldGenLearnsets":[]},"zwirrfinst":{"game":"PT","exists":true,"name":"zwirrfinst","eggGroup1":"Amorph","eggGroup2":"","gender":"both","lowestEvo":"zwirrlicht","evolutions":[],"unpairable":false,"unbreedable":true,"directLearnsets":["Eissturm","Groll","Lehmschelle","Schnarcher","Tiefschlag","Trickbetrug","Unheilböen"],"breedingLearnsets":[],"eventLearnsets":[],"oldGenLearnsets":[]},"zwirrklop":{"game":"PT","exists":true,"name":"zwirrklop","eggGroup1":"Amorph","eggGroup2":"","gender":"both","lowestEvo":"zwirrlicht","evolutions":["zwirrfinst"],"unpairable":false,"unbreedable":true,"directLearnsets":["Eissturm","Groll","Lehmschelle","Schnarcher","Tiefschlag","Trickbetrug","Unheilböen"],"breedingLearnsets":[],"eventLearnsets":[],"oldGenLearnsets":[]},"zwirrlicht":{"game":"PT","exists":true,"name":"zwirrlicht","eggGroup1":"Amorph","eggGroup2":"","gender":"both","lowestEvo":"zwirrlicht","evolutions":["zwirrklop","zwirrfinst"],"unpairable":false,"unbreedable":false,"directLearnsets":["Eissturm","Groll","Schnarcher","Tiefschlag","Trickbetrug","Unheilböen"],"breedingLearnsets":[],"eventLearnsets":[],"oldGenLearnsets":[]},"zwollock":{"game":"PT","exists":false,"name":"zwollock","eggGroup1":"Feld","eggGroup2":"","gender":"both","lowestEvo":"wolly","evolutions":[],"unpairable":false,"unbreedable":true,"directLearnsets":[],"breedingLearnsets":[],"eventLearnsets":[],"oldGenLearnsets":[]},"zwottronin":{"game":"PT","exists":false,"name":"zwottronin","eggGroup1":"Feld","eggGroup2":"","gender":"both","lowestEvo":"ottaro","evolutions":["admurai","hisui-admurai"],"unpairable":false,"unbreedable":true,"directLearnsets":[],"breedingLearnsets":[],"eventLearnsets":[],"oldGenLearnsets":[]},"zygarde":{"game":"PT","exists":false,"name":"zygarde","eggGroup1":"Unbekannt","eggGroup2":"","gender":"unknown","lowestEvo":"zygarde","evolutions":[],"unpairable":true,"unbreedable":true,"directLearnsets":[],"breedingLearnsets":[],"eventLearnsets":[],"oldGenLearnsets":[]},"zytomega":{"game":"PT","exists":false,"name":"zytomega","eggGroup1":"Amorph","eggGroup2":"","gender":"both","lowestEvo":"monozyto","evolutions":[],"unpairable":false,"unbreedable":true,"directLearnsets":[],"breedingLearnsets":[],"eventLearnsets":[],"oldGenLearnsets":[]}}